beedumper/__init__.py
beedumper/cli.py
beedumper/export.py
config.template.yaml
beedumper-0.1.6.dist-info/entry_points.txt
beedumper-0.1.6.dist-info/LICENSE
beedumper-0.1.6.dist-info/WHEEL
beedumper-0.1.6.dist-info/METADATA
beedumper-0.1.6.dist-info/RECORD
