Metadata-Version: 2.1
Name: beedumper
Version: 0.1.6
Summary: Exporting SupportBee data for better integration with other ticketing tools
Home-page: https://github.com/CartoDB/beedumper
License: MIT
Keywords: supportbee,backup
Author: Jorge Sanz
Author-email: jsanz@carto.com
Requires-Python: >=3.6,<4.0
Classifier: Development Status :: 4 - Beta
Classifier: Environment :: Console
Classifier: Intended Audience :: Customer Service
Classifier: Intended Audience :: Information Technology
Classifier: License :: OSI Approved :: MIT License
Classifier: Natural Language :: English
Classifier: Programming Language :: Python :: 3
Classifier: Programming Language :: Python :: 3.6
Classifier: Programming Language :: Python :: 3.7
Classifier: Topic :: Office/Business
Classifier: Topic :: Software Development :: Libraries :: Python Modules
Classifier: Topic :: System :: Archiving :: Backup
Classifier: Topic :: System :: Systems Administration
Requires-Dist: PyYAML (>=5.1,<6.0)
Requires-Dist: click (>=7.0,<8.0)
Requires-Dist: dateparser (>=0.7.1,<0.8.0)
Requires-Dist: pathos (>=0.2.3,<0.3.0)
Requires-Dist: requests (>=2.21,<3.0)
Project-URL: Repository, https://github.com/CartoDB/beedumper
